database_builder/__init__.py
database_builder/fields.txt
herschelhelp/__init__.py
herschelhelp/commands.py
herschelhelp/cutouts_dl.py
herschelhelp/cutouts_server.py
herschelhelp/database.py
herschelhelp/depth_coverage.py
herschelhelp/external.py
herschelhelp/filters.py
herschelhelp/footprints.py
herschelhelp/image_plotting.py
herschelhelp/utils.py
herschelhelp-1.0.3.dist-info/LICENSE
herschelhelp-1.0.3.dist-info/METADATA
herschelhelp-1.0.3.dist-info/WHEEL
herschelhelp-1.0.3.dist-info/entry_points.txt
herschelhelp-1.0.3.dist-info/top_level.txt
herschelhelp-1.0.3.dist-info/RECORD
