Metadata-Version: 2.1
Name: herschelhelp
Version: 1.0.3
Summary: HELP project module
Author: Yannick Roehlly
Author-email: yannick.roehlly@lam.fr
License: MIT
License-File: LICENSE
Requires-Dist: numpy
Requires-Dist: astropy
Requires-Dist: click
Requires-Dist: pymoc
Requires-Dist: pyvo
Requires-Dist: sqlalchemy
Requires-Dist: scipy
Requires-Dist: herschelhelp-internal
